windmillendpointmonitorv1/__init__.py
windmillendpointmonitorv1/client/__init__.py
windmillendpointmonitorv1/client/endpoint_monitor_client.py
windmill_endpoint_monitor-1.0.0.0.dist-info/METADATA
windmill_endpoint_monitor-1.0.0.0.dist-info/WHEEL
windmill_endpoint_monitor-1.0.0.0.dist-info/top_level.txt
windmill_endpoint_monitor-1.0.0.0.dist-info/RECORD
